peaklets/__init__.py
peaklets/peaklets.py
peaklets/tests/__init__.py
peaklets/tests/test_peaklets.py
peaklets-0.1.1.dist-info/METADATA
peaklets-0.1.1.dist-info/WHEEL
peaklets-0.1.1.dist-info/top_level.txt
peaklets-0.1.1.dist-info/RECORD
