Metadata-Version: 2.1
Name: peaklets
Version: 0.1.1
Summary: Decompose a 1D positive signal using only positive basis functions
Author-email: "Charles C. Kankelborg" <kankel@montana.edu>, "Roy T. Smart" <roytsmart@gmail.com>
Project-URL: Homepage, https://github.com/Kankelborg-Group/peaklets
Classifier: Programming Language :: Python :: 3
Requires-Python: >=3.7
Requires-Dist: numpy
Requires-Dist: numba
Provides-Extra: doc
Requires-Dist: sphinx-autodoc-typehints ; extra == 'doc'
Requires-Dist: pydata-sphinx-theme ; extra == 'doc'
Requires-Dist: jupyter-sphinx ; extra == 'doc'
Provides-Extra: test
Requires-Dist: pytest ; extra == 'test'
